sqlalchemy_drill/__init__.py
sqlalchemy_drill/base.py
sqlalchemy_drill/jdbc.py
sqlalchemy_drill/odbc.py
sqlalchemy_drill/sadrill.py
sqlalchemy_drill/drilldbapi/__init__.py
sqlalchemy_drill/drilldbapi/_drilldbapi.py
sqlalchemy_drill/drilldbapi/api_exceptions.py
sqlalchemy_drill/drilldbapi/api_globals.py
sqlalchemy_drill-1.1.9.dist-info/licenses/AUTHORS
sqlalchemy_drill-1.1.9.dist-info/licenses/LICENSE
test/__init__.py
test/conftest.py
test/dbapi20.py
test/test_dbapi_compliance.py
test/test_jars.py
test/test_jdbc.py
test/test_odbc.py
test/test_sadrill.py
test/test_suite.py
sqlalchemy_drill-1.1.9.dist-info/METADATA
sqlalchemy_drill-1.1.9.dist-info/WHEEL
sqlalchemy_drill-1.1.9.dist-info/entry_points.txt
sqlalchemy_drill-1.1.9.dist-info/top_level.txt
sqlalchemy_drill-1.1.9.dist-info/RECORD
