Metadata-Version: 2.4
Name: sqlalchemy_drill
Version: 1.1.9
Summary: Apache Drill for SQLAlchemy
Home-page: https://github.com/JohnOmernik/sqlalchemy-drill
Download-URL: https://github.com/JohnOmernik/sqlalchemy-drill/archive/1.1.9.tar.gz
Author: John Omernik, Charles Givre, Davide Miceli, Massimo Martiradonna, James Turton
Author-email: john@omernik.com, cgivre@thedataist.com, davide.miceli.dap@gmail.com, massimo.martiradonna.dap@gmail.com, james@somecomputer.xyz
License: MIT
Keywords: SQLAlchemy Apache Drill
Classifier: Development Status :: 5 - Production/Stable
Classifier: Environment :: Console
Classifier: License :: OSI Approved :: MIT License
Classifier: Intended Audience :: Developers
Classifier: Programming Language :: Python
Classifier: Programming Language :: Python :: 3
Classifier: Programming Language :: Python :: 3.6
Classifier: Programming Language :: Python :: 3.7
Classifier: Programming Language :: Python :: 3.8
Classifier: Programming Language :: Python :: 3.9
Classifier: Programming Language :: Python :: Implementation :: CPython
Classifier: Topic :: Database :: Front-Ends
License-File: LICENSE
License-File: AUTHORS
Requires-Dist: requests
Requires-Dist: ijson
Requires-Dist: sqlalchemy
Provides-Extra: jdbc
Requires-Dist: JPype1; extra == "jdbc"
Requires-Dist: JayDeBeApi; extra == "jdbc"
Provides-Extra: odbc
Requires-Dist: pyodbc; extra == "odbc"
Dynamic: author
Dynamic: author-email
Dynamic: classifier
Dynamic: description
Dynamic: description-content-type
Dynamic: download-url
Dynamic: home-page
Dynamic: keywords
Dynamic: license
Dynamic: license-file
Dynamic: provides-extra
Dynamic: requires-dist
Dynamic: summary
